chapsnap/__init__.py
chapsnap/main.py
chapsnap-1.2.0.dist-info/LICENSE
chapsnap-1.2.0.dist-info/METADATA
chapsnap-1.2.0.dist-info/WHEEL
chapsnap-1.2.0.dist-info/entry_points.txt
chapsnap-1.2.0.dist-info/RECORD
